{"ADV01":{"description": "Agency Qualifier Code", "required": "M", "min_length": "2", "max_length": "2", "type": "ID"},"ADV02":{"description": "Service Characteristics Qualifier", "required": "M", "min_length": "2", "max_length": "3", "type": "AN"},"ADV03":{"description": "Range Minimum", "required": "O", "min_length": "1", "max_length": "20", "type": "R"},"ADV04":{"description": "Range Maximum", "required": "O", "min_length": "1", "max_length": "20", "type": "R"},"ADV05":{"description": "Category", "required": "O", "min_length": "1", "max_length": "6", "type": "AN"},"ADV06":{"description": "Service Characteristics Qualifier", "required": "C", "min_length": "2", "max_length": "3", "type": "AN"},"ADV07":{"description": "Measurement Value", "required": "C", "min_length": "1", "max_length": "20", "type": "R"}}