{"FOB01":{"description": "Shipment Method Of Payment", "required": "M", "min_length": "2", "max_length": "2", "type": "ID"},"FOB02":{"description": "Location Qualifier", "required": "C", "min_length": "1", "max_length": "2", "type": "ID"},"FOB03":{"description": "Description", "required": "O", "min_length": "1", "max_length": "80", "type": "AN"},"FOB04":{"description": "Transportation Terms Qualifier Code", "required": "O", "min_length": "2", "max_length": "2", "type": "ID"},"FOB05":{"description": "Transportation Terms Code", "required": "C", "min_length": "3", "max_length": "3", "type": "ID"},"FOB06":{"description": "Location Qualifier", "required": "C", "min_length": "1", "max_length": "2", "type": "ID"},"FOB07":{"description": "Description", "required": "O", "min_length": "1", "max_length": "80", "type": "AN"},"FOB08":{"description": "Risk Of Loss Code", "required": "O", "min_length": "2", "max_length": "2", "type": "ID"},"FOB09":{"description": "Description", "required": "C", "min_length": "1", "max_length": "80", "type": "AN"}}